bot_linkedin
