Metadata-Version: 2.1
Name: linkedin-bot
Version: 1.0.1
Summary: This library allow to do automatisation actions like, share and comment on social network
Home-page: https://gitlab.kaisens.fr/amouhite02/automatisation-rs
Author: ADEBO
Author-email: madebo@kaisensdata.fr
License: MIT
Keywords: linkedin,bot,bot_linkedin,automatisation
Platform: UNKNOWN
Classifier: Programming Language :: Python :: 3.8
Classifier: Operating System :: OS Independent
Requires-Python: >=3.5
